craft_text_detector/__init__.py
craft_text_detector/craft_utils.py
craft_text_detector/file_utils.py
craft_text_detector/image_utils.py
craft_text_detector/predict.py
craft_text_detector/torch_utils.py
craft_text_detector/models/__init__.py
craft_text_detector/models/craftnet.py
craft_text_detector/models/refinenet.py
craft_text_detector/models/basenet/__init__.py
craft_text_detector/models/basenet/vgg16_bn.py
craft_text_detector_updated-0.4.7.dist-info/LICENSE
craft_text_detector_updated-0.4.7.dist-info/METADATA
craft_text_detector_updated-0.4.7.dist-info/WHEEL
craft_text_detector_updated-0.4.7.dist-info/top_level.txt
craft_text_detector_updated-0.4.7.dist-info/RECORD
